{"919055561bcc131bd0c51d493a86f529":{"statistic":{"failed":0,"broken":0,"skipped":0,"passed":1,"unknown":0,"total":1},"items":[{"uid":"4287547b32c75b14","reportUrl":"https://enokjanuario.github.io/dota2-api-test/18//#testresult/4287547b32c75b14","status":"passed","time":{"start":1744234719418,"stop":1744234719686,"duration":268}}]},"ad32a964a78494f4aa10986dc69b3e4b":{"statistic":{"failed":0,"broken":0,"skipped":0,"passed":1,"unknown":0,"total":1},"items":[{"uid":"3d69c7e68f428b0a","reportUrl":"https://enokjanuario.github.io/dota2-api-test/18//#testresult/3d69c7e68f428b0a","status":"passed","time":{"start":1744234723266,"stop":1744234723555,"duration":289}}]},"b9d4d35e86fbca74a8232cb14c03cf55":{"statistic":{"failed":0,"broken":0,"skipped":0,"passed":1,"unknown":0,"total":1},"items":[{"uid":"caaf930f5bb0679e","reportUrl":"https://enokjanuario.github.io/dota2-api-test/18//#testresult/caaf930f5bb0679e","status":"passed","time":{"start":1744234721835,"stop":1744234722105,"duration":270}}]},"27502e502675b867638aa101cbdbe858":{"statistic":{"failed":0,"broken":0,"skipped":0,"passed":1,"unknown":0,"total":1},"items":[{"uid":"26350f68a394af1","reportUrl":"https://enokjanuario.github.io/dota2-api-test/18//#testresult/26350f68a394af1","status":"passed","time":{"start":1744234716247,"stop":1744234718963,"duration":2716}}]},"cbc9a6e3a77161606c51839794a49b10":{"statistic":{"failed":0,"broken":0,"skipped":0,"passed":1,"unknown":0,"total":1},"items":[{"uid":"329d8fd6152db1e6","reportUrl":"https://enokjanuario.github.io/dota2-api-test/18//#testresult/329d8fd6152db1e6","status":"passed","time":{"start":1744234719807,"stop":1744234721829,"duration":2022}}]},"ade71ff60d2c5d369c3f6f19631fba64":{"statistic":{"failed":0,"broken":0,"skipped":0,"passed":1,"unknown":0,"total":1},"items":[{"uid":"462dd3ce7938eb3e","reportUrl":"https://enokjanuario.github.io/dota2-api-test/18//#testresult/462dd3ce7938eb3e","status":"passed","time":{"start":1744234716253,"stop":1744234721784,"duration":5531}}]},"6cf9ac78af295de8426dbf8f50228afa":{"statistic":{"failed":0,"broken":0,"skipped":0,"passed":1,"unknown":0,"total":1},"items":[{"uid":"ca03dad27e93c672","reportUrl":"https://enokjanuario.github.io/dota2-api-test/18//#testresult/ca03dad27e93c672","status":"passed","time":{"start":1744234722113,"stop":1744234722362,"duration":249}}]},"c3e657d7df238775bb3edb195dc06107":{"statistic":{"failed":0,"broken":0,"skipped":0,"passed":1,"unknown":0,"total":1},"items":[{"uid":"b1815e867ccd06aa","reportUrl":"https://enokjanuario.github.io/dota2-api-test/18//#testresult/b1815e867ccd06aa","status":"passed","time":{"start":1744234721606,"stop":1744234721833,"duration":227}}]},"17e5619f1e8d6817569f465d87a0ee82":{"statistic":{"failed":0,"broken":0,"skipped":0,"passed":1,"unknown":0,"total":1},"items":[{"uid":"fe9493a3b0c19ca","reportUrl":"https://enokjanuario.github.io/dota2-api-test/18//#testresult/fe9493a3b0c19ca","status":"passed","time":{"start":1744234722806,"stop":1744234723175,"duration":369}}]},"d72f8865c5ef46f41b868657def579e9":{"statistic":{"failed":0,"broken":0,"skipped":0,"passed":1,"unknown":0,"total":1},"items":[{"uid":"bc8f376b942e03fe","reportUrl":"https://enokjanuario.github.io/dota2-api-test/18//#testresult/bc8f376b942e03fe","status":"passed","time":{"start":1744234721346,"stop":1744234721597,"duration":251}}]},"e1b9a1f1051011faf9958d1687634e9f":{"statistic":{"failed":0,"broken":0,"skipped":0,"passed":1,"unknown":0,"total":1},"items":[{"uid":"d0ff11baf31e82f0","reportUrl":"https://enokjanuario.github.io/dota2-api-test/18//#testresult/d0ff11baf31e82f0","status":"passed","time":{"start":1744234722340,"stop":1744234722638,"duration":298}}]},"178803d72efa9856816a2d25fbde56e":{"statistic":{"failed":0,"broken":0,"skipped":0,"passed":1,"unknown":0,"total":1},"items":[{"uid":"dd8857347dfb182c","reportUrl":"https://enokjanuario.github.io/dota2-api-test/18//#testresult/dd8857347dfb182c","status":"passed","time":{"start":1744234716250,"stop":1744234718147,"duration":1897}}]},"29b81f2e9dc0bf9a0a03831935cf30a3":{"statistic":{"failed":0,"broken":0,"skipped":0,"passed":1,"unknown":0,"total":1},"items":[{"uid":"4eb3fa8cce41d2c1","reportUrl":"https://enokjanuario.github.io/dota2-api-test/18//#testresult/4eb3fa8cce41d2c1","status":"passed","time":{"start":1744234722746,"stop":1744234723022,"duration":276}}]},"99b8b753b8267b59033f7b87df602606":{"statistic":{"failed":0,"broken":0,"skipped":0,"passed":1,"unknown":0,"total":1},"items":[{"uid":"1529c4dbf5ad289b","reportUrl":"https://enokjanuario.github.io/dota2-api-test/18//#testresult/1529c4dbf5ad289b","status":"passed","time":{"start":1744234723485,"stop":1744234723489,"duration":4}}]},"d1d4203605095cfd7ee4be88c4887e65":{"statistic":{"failed":0,"broken":0,"skipped":0,"passed":1,"unknown":0,"total":1},"items":[{"uid":"f4e7ea94b700dfef","reportUrl":"https://enokjanuario.github.io/dota2-api-test/18//#testresult/f4e7ea94b700dfef","status":"passed","time":{"start":1744234722081,"stop":1744234722298,"duration":217}}]},"7b38429dee045c192939f1a818f43fa1":{"statistic":{"failed":0,"broken":0,"skipped":0,"passed":1,"unknown":0,"total":1},"items":[{"uid":"e623da6fefb05f4c","reportUrl":"https://enokjanuario.github.io/dota2-api-test/18//#testresult/e623da6fefb05f4c","status":"passed","time":{"start":1744234722642,"stop":1744234722886,"duration":244}}]},"8ef2d11dc1db0718b0bdccbb0be4b44a":{"statistic":{"failed":0,"broken":0,"skipped":0,"passed":1,"unknown":0,"total":1},"items":[{"uid":"b84ce5a16ce0248","reportUrl":"https://enokjanuario.github.io/dota2-api-test/18//#testresult/b84ce5a16ce0248","status":"passed","time":{"start":1744234718341,"stop":1744234719582,"duration":1241}}]},"ec5654f9da57b1af6fb21048994c03d2":{"statistic":{"failed":0,"broken":0,"skipped":0,"passed":1,"unknown":0,"total":1},"items":[{"uid":"beab4592bf2181e5","reportUrl":"https://enokjanuario.github.io/dota2-api-test/18//#testresult/beab4592bf2181e5","status":"passed","time":{"start":1744234723479,"stop":1744234723483,"duration":4}}]},"86e3aa505c77d04db1d03e71f2ca96bc":{"statistic":{"failed":0,"broken":0,"skipped":0,"passed":1,"unknown":0,"total":1},"items":[{"uid":"c8790024ca7fc86b","reportUrl":"https://enokjanuario.github.io/dota2-api-test/18//#testresult/c8790024ca7fc86b","status":"passed","time":{"start":1744234723025,"stop":1744234723322,"duration":297}}]},"e286bbf089f590732e991276b42a4c6d":{"statistic":{"failed":0,"broken":0,"skipped":0,"passed":1,"unknown":0,"total":1},"items":[{"uid":"e03ff9588c8abda0","reportUrl":"https://enokjanuario.github.io/dota2-api-test/18//#testresult/e03ff9588c8abda0","status":"passed","time":{"start":1744234720477,"stop":1744234721336,"duration":859}}]},"4cc33d7ed2df90246b9ead1d08a74c8c":{"statistic":{"failed":0,"broken":0,"skipped":0,"passed":1,"unknown":0,"total":1},"items":[{"uid":"fba692eec9ea071a","reportUrl":"https://enokjanuario.github.io/dota2-api-test/18//#testresult/fba692eec9ea071a","status":"passed","time":{"start":1744234723251,"stop":1744234723616,"duration":365}}]},"583b090da698f58dbdc7012ef788c9ef":{"statistic":{"failed":0,"broken":0,"skipped":0,"passed":1,"unknown":0,"total":1},"items":[{"uid":"1e76cdf4065603f","reportUrl":"https://enokjanuario.github.io/dota2-api-test/18//#testresult/1e76cdf4065603f","status":"passed","time":{"start":1744234722749,"stop":1744234723052,"duration":303}}]},"49eebbb4759c58f7b14a998d486dae11":{"statistic":{"failed":0,"broken":0,"skipped":0,"passed":1,"unknown":0,"total":1},"items":[{"uid":"7c6a346941cd9a43","reportUrl":"https://enokjanuario.github.io/dota2-api-test/18//#testresult/7c6a346941cd9a43","status":"passed","time":{"start":1744234719693,"stop":1744234720843,"duration":1150}}]},"9c2605b8cec3e2a960869bc68eff9929":{"statistic":{"failed":0,"broken":0,"skipped":0,"passed":1,"unknown":0,"total":1},"items":[{"uid":"a2c883ce3913de33","reportUrl":"https://enokjanuario.github.io/dota2-api-test/18//#testresult/a2c883ce3913de33","status":"passed","time":{"start":1744234722073,"stop":1744234722334,"duration":261}}]},"36ea1022a2fbf4dea89660408da5056a":{"statistic":{"failed":0,"broken":0,"skipped":0,"passed":1,"unknown":0,"total":1},"items":[{"uid":"394b88b28f6fb6a8","reportUrl":"https://enokjanuario.github.io/dota2-api-test/18//#testresult/394b88b28f6fb6a8","status":"passed","time":{"start":1744234723178,"stop":1744234723465,"duration":287}}]},"e59f8939c48ef5aaae7a8b9ae8f33196":{"statistic":{"failed":0,"broken":0,"skipped":0,"passed":1,"unknown":0,"total":1},"items":[{"uid":"a3ef1cf45d3d2d6d","reportUrl":"https://enokjanuario.github.io/dota2-api-test/18//#testresult/a3ef1cf45d3d2d6d","status":"passed","time":{"start":1744234721836,"stop":1744234722388,"duration":552}}]},"e411d0c82e0d46e5bdc5681fd3dd2d7b":{"statistic":{"failed":0,"broken":0,"skipped":0,"passed":1,"unknown":0,"total":1},"items":[{"uid":"5fcc3c5aa3f1bfe8","reportUrl":"https://enokjanuario.github.io/dota2-api-test/18//#testresult/5fcc3c5aa3f1bfe8","status":"passed","time":{"start":1744234723328,"stop":1744234723610,"duration":282}}]},"97534750130ee4d6d69bf1d967bcb699":{"statistic":{"failed":0,"broken":0,"skipped":0,"passed":1,"unknown":0,"total":1},"items":[{"uid":"e736781182c16d5c","reportUrl":"https://enokjanuario.github.io/dota2-api-test/18//#testresult/e736781182c16d5c","status":"passed","time":{"start":1744234722300,"stop":1744234722797,"duration":497}}]},"164fdb8e0fe318cf5148946aaecf04b9":{"statistic":{"failed":0,"broken":0,"skipped":0,"passed":1,"unknown":0,"total":1},"items":[{"uid":"e09be118203b277f","reportUrl":"https://enokjanuario.github.io/dota2-api-test/18//#testresult/e09be118203b277f","status":"passed","time":{"start":1744234723055,"stop":1744234723242,"duration":187}}]},"f6c21f856d744e552a993be89832b3a3":{"statistic":{"failed":0,"broken":0,"skipped":0,"passed":1,"unknown":0,"total":1},"items":[{"uid":"7a0edd2ed204972a","reportUrl":"https://enokjanuario.github.io/dota2-api-test/18//#testresult/7a0edd2ed204972a","status":"passed","time":{"start":1744234722889,"stop":1744234723261,"duration":372}}]},"4c5f7547032508fefa32f5e067cbba5e":{"statistic":{"failed":0,"broken":0,"skipped":0,"passed":1,"unknown":0,"total":1},"items":[{"uid":"643d2913e15244f1","reportUrl":"https://enokjanuario.github.io/dota2-api-test/18//#testresult/643d2913e15244f1","status":"passed","time":{"start":1744234716250,"stop":1744234719404,"duration":3154}}]},"6ea41934097a1e6287ca00fe18133db0":{"statistic":{"failed":0,"broken":0,"skipped":0,"passed":1,"unknown":0,"total":1},"items":[{"uid":"b176a22c6131b6e4","reportUrl":"https://enokjanuario.github.io/dota2-api-test/18//#testresult/b176a22c6131b6e4","status":"passed","time":{"start":1744234719590,"stop":1744234720464,"duration":874}}]},"fc168749c38f7d9b697eaa206b846e6e":{"statistic":{"failed":0,"broken":0,"skipped":0,"passed":1,"unknown":0,"total":1},"items":[{"uid":"b9bdef029a41ed67","reportUrl":"https://enokjanuario.github.io/dota2-api-test/18//#testresult/b9bdef029a41ed67","status":"passed","time":{"start":1744234722365,"stop":1744234722743,"duration":378}}]},"e073df41bbff4aecd4d5e9d1698eb87f":{"statistic":{"failed":0,"broken":0,"skipped":0,"passed":1,"unknown":0,"total":1},"items":[{"uid":"5fcaca742b453276","reportUrl":"https://enokjanuario.github.io/dota2-api-test/18//#testresult/5fcaca742b453276","status":"passed","time":{"start":1744234722396,"stop":1744234722743,"duration":347}}]},"9b3e1d1d9b762cc460397e68086b3f40":{"statistic":{"failed":0,"broken":0,"skipped":0,"passed":1,"unknown":0,"total":1},"items":[{"uid":"cc6b47cbbe0d484d","reportUrl":"https://enokjanuario.github.io/dota2-api-test/18//#testresult/cc6b47cbbe0d484d","status":"passed","time":{"start":1744234723470,"stop":1744234723477,"duration":7}}]},"4604f7d5c80c35ffca55693dd56b936e":{"statistic":{"failed":0,"broken":0,"skipped":0,"passed":1,"unknown":0,"total":1},"items":[{"uid":"cc8b964f9415b804","reportUrl":"https://enokjanuario.github.io/dota2-api-test/18//#testresult/cc8b964f9415b804","status":"passed","time":{"start":1744234718974,"stop":1744234719803,"duration":829}}]},"1894c000d20c59d2a16922492fd98cf4":{"statistic":{"failed":0,"broken":0,"skipped":0,"passed":1,"unknown":0,"total":1},"items":[{"uid":"3ac6a06122dd5e82","reportUrl":"https://enokjanuario.github.io/dota2-api-test/18//#testresult/3ac6a06122dd5e82","status":"passed","time":{"start":1744234721792,"stop":1744234722079,"duration":287}}]},"8c99aa25b97dffee2d6645ec7929a774":{"statistic":{"failed":0,"broken":0,"skipped":0,"passed":1,"unknown":0,"total":1},"items":[{"uid":"4089eca52abe1cb9","reportUrl":"https://enokjanuario.github.io/dota2-api-test/18//#testresult/4089eca52abe1cb9","status":"passed","time":{"start":1744234720849,"stop":1744234722070,"duration":1221}}]}}